gasoptics/__init__.py
gasoptics/equations_of_state/__init__.py
gasoptics/equations_of_state/peng_robinson.py
gasoptics/equations_of_state/virial.py
gasoptics/thermodynamics/__init__.py
gasoptics/thermodynamics/compressibility.py
gasoptics/thermodynamics/constants.py
gasoptics/thermodynamics/enthalpy_entropy.py
gasoptics/thermodynamics/helmholtz_gibbs.py
gasoptics/thermodynamics/kinematic_thermal.py
gasoptics/thermodynamics/specific_heat.py
gasoptics/thermodynamics/state.py
gasoptics/transport/__init__.py
gasoptics/transport/diffusivity.py
gasoptics/transport/thermal_conductivity.py
gasoptics/transport/viscosity.py
gasoptics/utils/__init__.py
gasoptics/utils/constants.py
gasoptics/utils/conversions.py
Gasoptics_ali91en-0.1.0.dist-info/LICENSE.txt
Gasoptics_ali91en-0.1.0.dist-info/METADATA
Gasoptics_ali91en-0.1.0.dist-info/WHEEL
Gasoptics_ali91en-0.1.0.dist-info/top_level.txt
Gasoptics_ali91en-0.1.0.dist-info/RECORD
